{
  "ID": "60b03c0b-635b-418c-b1cd-b13130223591",
  "Version": "2.3.4",
  "Name": "GameBoardInfoUI",
  "Content": {
    "Content": {
      "Animation": {
        "Duration": 0,
        "Speed": 1.0,
        "Timelines": [],
        "ctype": "TimelineActionData"
      },
      "AnimationList": [],
      "ObjectData": {
        "Tag": 508,
        "Children": [
          {
            "ClipAble": false,
            "BackColorAlpha": 102,
            "SingleColor": {
              "R": 150,
              "G": 200
            },
            "FirstColor": {
              "R": 150,
              "G": 200
            },
            "EndColor": {},
            "ColorVector": {
              "ScaleY": 1.0
            },
            "Scale9Width": 1,
            "Scale9Height": 1,
            "AnchorPoint": {
              "ScaleX": 0.5,
              "ScaleY": 1.0
            },
            "Position": {
              "X": 360.0,
              "Y": 1280.0
            },
            "Scale": {
              "ScaleX": 1.0,
              "ScaleY": 1.0
            },
            "CColor": {},
            "IconVisible": false,
            "PositionPercentXEnabled": true,
            "PositionPercentYEnabled": true,
            "PrePosition": {
              "X": 0.5,
              "Y": 1.0
            },
            "PercentWidthEnable": true,
            "PercentWidthEnabled": true,
            "PreSize": {
              "X": 1.0,
              "Y": 0.0
            },
            "BottomMargin": 1280.0,
            "Tag": 147,
            "Children": [
              {
                "FileData": {
                  "Type": "Normal",
                  "Path": "game/gui/board_info/bg_top.png",
                  "Plist": ""
                },
                "Scale9Enable": true,
                "Scale9OriginX": 237,
                "Scale9Width": 188,
                "Scale9Height": 174,
                "AnchorPoint": {
                  "ScaleX": 0.45,
                  "ScaleY": 0.5
                },
                "Position": {
                  "X": 360.0,
                  "Y": -147.0
                },
                "Scale": {
                  "ScaleX": 1.0,
                  "ScaleY": 1.0
                },
                "CColor": {},
                "IconVisible": false,
                "PositionPercentXEnabled": true,
                "PrePosition": {
                  "X": 0.5,
                  "Y": 0.0
                },
                "PreSize": {
                  "X": 0.9194,
                  "Y": 0.0
                },
                "VerticalEdge": "TopEdge",
                "LeftMargin": 62.1,
                "RightMargin": -4.1,
                "TopMargin": 60.0,
                "BottomMargin": -234.0,
                "Tag": 512,
                "Children": [
                  {
                    "FileData": {
                      "Type": "Normal",
                      "Path": "game/gui/board_info/bg_move.png",
                      "Plist": ""
                    },
                    "BlendFunc": {
                      "Src": 1,
                      "Dst": 771
                    },
                    "AnchorPoint": {
                      "ScaleX": 1.0,
                      "ScaleY": 0.5
                    },
                    "Position": {
                      "X": 642.0,
                      "Y": 84.2656
                    },
                    "Scale": {
                      "ScaleX": 1.0,
                      "ScaleY": 1.0
                    },
                    "CColor": {},
                    "IconVisible": false,
                    "PrePosition": {
                      "X": 0.9698,
                      "Y": 0.4843
                    },
                    "PreSize": {
                      "X": 0.1934,
                      "Y": 0.6207
                    },
                    "HorizontalEdge": "RightEdge",
                    "LeftMargin": 514.0,
                    "RightMargin": 20.0,
                    "TopMargin": 35.7344,
                    "BottomMargin": 30.2656,
                    "Tag": 516,
                    "Children": [
                      {
                        "IsCustomSize": true,
                        "FontSize": 45,
                        "LabelText": "25",
                        "FontResource": {
                          "Type": "Normal",
                          "Path": "font/BalooPaaji2-ExtraBold.ttf",
                          "Plist": ""
                        },
                        "HorizontalAlignmentType": "HT_Center",
                        "VerticalAlignmentType": "VT_Center",
                        "OutlineColor": {
                          "R": 159,
                          "G": 84,
                          "B": 93
                        },
                        "ShadowColor": {
                          "R": 110,
                          "G": 110,
                          "B": 110
                        },
                        "ShadowOffsetX": 2.0,
                        "ShadowOffsetY": -2.0,
                        "AnchorPoint": {
                          "ScaleX": 0.4951,
                          "ScaleY": 0.5
                        },
                        "Position": {
                          "X": 64.0,
                          "Y": 40.0
                        },
                        "Scale": {
                          "ScaleX": 1.0,
                          "ScaleY": 1.0
                        },
                        "CColor": {
                          "R": 70,
                          "G": 48,
                          "B": 196
                        },
                        "IconVisible": false,
                        "PositionPercentXEnabled": true,
                        "PrePosition": {
                          "X": 0.5,
                          "Y": 0.3704
                        },
                        "PreSize": {
                          "X": 0.7812,
                          "Y": 0.463
                        },
                        "LeftMargin": 14.49,
                        "RightMargin": 13.51,
                        "TopMargin": 43.0,
                        "BottomMargin": 15.0,
                        "Tag": 519,
                        "ActionTag": -1809123306,
                        "Size": {
                          "X": 100.0,
                          "Y": 50.0
                        },
                        "Name": "lbMove",
                        "ctype": "TextObjectData"
                      },
                      {
                        "IsCustomSize": true,
                        "FontSize": 30,
                        "LabelText": "Move",
                        "FontResource": {
                          "Type": "Normal",
                          "Path": "font/BalooPaaji2-ExtraBold.ttf",
                          "Plist": ""
                        },
                        "HorizontalAlignmentType": "HT_Center",
                        "VerticalAlignmentType": "VT_Center",
                        "OutlineSize": 2,
                        "OutlineColor": {
                          "R": 64,
                          "G": 98,
                          "B": 212
                        },
                        "OutlineEnabled": true,
                        "ShadowColor": {
                          "R": 110,
                          "G": 110,
                          "B": 110
                        },
                        "ShadowOffsetX": 2.0,
                        "ShadowOffsetY": -2.0,
                        "AnchorPoint": {
                          "ScaleX": 0.4951,
                          "ScaleY": 0.5
                        },
                        "Position": {
                          "X": 64.0,
                          "Y": 90.0
                        },
                        "Scale": {
                          "ScaleX": 1.0,
                          "ScaleY": 1.0
                        },
                        "CColor": {},
                        "IconVisible": false,
                        "PositionPercentXEnabled": true,
                        "PrePosition": {
                          "X": 0.5,
                          "Y": 0.8333
                        },
                        "PreSize": {
                          "X": 0.7812,
                          "Y": 0.463
                        },
                        "LeftMargin": 14.49,
                        "RightMargin": 13.51,
                        "TopMargin": -7.0,
                        "BottomMargin": 65.0,
                        "Tag": 140,
                        "ActionTag": -297234279,
                        "Size": {
                          "X": 100.0,
                          "Y": 50.0
                        },
                        "Name": "lbMoveTitle",
                        "ctype": "TextObjectData"
                      }
                    ],
                    "ActionTag": -1037822725,
                    "Size": {
                      "X": 128.0,
                      "Y": 108.0
                    },
                    "Name": "bg_move",
                    "ctype": "SpriteObjectData"
                  },
                  {
                    "FileData": {
                      "Type": "Normal",
                      "Path": "game/gui/board_info/bg_cat.png",
                      "Plist": ""
                    },
                    "Scale9OriginX": 60,
                    "Scale9OriginY": 60,
                    "Scale9Width": 63,
                    "Scale9Height": 63,
                    "AnchorPoint": {
                      "ScaleX": 0.5,
                      "ScaleY": 0.5
                    },
                    "Position": {
                      "X": 40.0,
                      "Y": 87.0
                    },
                    "Scale": {
                      "ScaleX": 1.0,
                      "ScaleY": 1.0
                    },
                    "CColor": {},
                    "IconVisible": false,
                    "PositionPercentYEnabled": true,
                    "PrePosition": {
                      "X": 0.0604,
                      "Y": 0.5
                    },
                    "PreSize": {
                      "X": 0.2764,
                      "Y": 1.0517
                    },
                    "LeftMargin": -51.5,
                    "RightMargin": 530.5,
                    "TopMargin": -4.5,
                    "BottomMargin": -4.5,
                    "Tag": 149,
                    "Children": [
                      {
                        "AnchorPoint": {},
                        "Position": {
                          "X": 91.5,
                          "Y": 10.0
                        },
                        "Scale": {
                          "ScaleX": 1.0,
                          "ScaleY": 1.0
                        },
                        "CColor": {},
                        "IconVisible": true,
                        "PositionPercentXEnabled": true,
                        "PrePosition": {
                          "X": 0.5,
                          "Y": 0.0546
                        },
                        "PreSize": {
                          "X": 0.0,
                          "Y": 0.0
                        },
                        "LeftMargin": 91.5,
                        "RightMargin": 91.5,
                        "TopMargin": 173.0,
                        "BottomMargin": 10.0,
                        "Tag": 151,
                        "ActionTag": 1170454581,
                        "Size": {
                          "X": 0.0,
                          "Y": 0.0
                        },
                        "Name": "nodeCat",
                        "ctype": "SingleNodeObjectData"
                      },
                      {
                        "FileData": {
                          "Type": "Normal",
                          "Path": "game/gui/board_info/bg_cat_border.png",
                          "Plist": ""
                        },
                        "Scale9OriginX": 61,
                        "Scale9OriginY": 62,
                        "Scale9Width": 65,
                        "Scale9Height": 65,
                        "AnchorPoint": {
                          "ScaleX": 0.5,
                          "ScaleY": 0.5
                        },
                        "Position": {
                          "X": 91.5,
                          "Y": 91.5
                        },
                        "Scale": {
                          "ScaleX": 1.0,
                          "ScaleY": 1.0
                        },
                        "CColor": {},
                        "IconVisible": false,
                        "PositionPercentXEnabled": true,
                        "PositionPercentYEnabled": true,
                        "PrePosition": {
                          "X": 0.5,
                          "Y": 0.5
                        },
                        "PreSize": {
                          "X": 1.0219,
                          "Y": 1.0328
                        },
                        "LeftMargin": -2.0,
                        "RightMargin": -2.0,
                        "TopMargin": -3.0,
                        "BottomMargin": -3.0,
                        "Tag": 150,
                        "ActionTag": 1387716621,
                        "Size": {
                          "X": 187.0,
                          "Y": 189.0
                        },
                        "Name": "borderCat",
                        "ctype": "ImageViewObjectData"
                      }
                    ],
                    "ActionTag": -302924824,
                    "Size": {
                      "X": 183.0,
                      "Y": 183.0
                    },
                    "Name": "bgCat",
                    "ctype": "ImageViewObjectData"
                  },
                  {
                    "ClipAble": false,
                    "BackColorAlpha": 102,
                    "SingleColor": {
                      "R": 150,
                      "G": 200
                    },
                    "FirstColor": {
                      "R": 150,
                      "G": 200
                    },
                    "EndColor": {},
                    "ColorVector": {
                      "ScaleY": 1.0
                    },
                    "Scale9Width": 1,
                    "Scale9Height": 1,
                    "AnchorPoint": {
                      "ScaleX": 0.5,
                      "ScaleY": 0.5
                    },
                    "Position": {
                      "X": 325.0,
                      "Y": 85.0
                    },
                    "Scale": {
                      "ScaleX": 1.0,
                      "ScaleY": 1.0
                    },
                    "CColor": {},
                    "IconVisible": false,
                    "PrePosition": {
                      "X": 0.4909,
                      "Y": 0.4885
                    },
                    "PreSize": {
                      "X": 0.3852,
                      "Y": 0.0
                    },
                    "LeftMargin": 197.5,
                    "RightMargin": 209.5,
                    "TopMargin": 89.0,
                    "BottomMargin": 85.0,
                    "Tag": 139,
                    "Children": [
                      {
                        "FileData": {
                          "Type": "Normal",
                          "Path": "game/gui/board_info/bg_objective.png",
                          "Plist": ""
                        },
                        "Scale9Enable": true,
                        "Scale9OriginX": 120,
                        "Scale9OriginY": 36,
                        "Scale9Width": 125,
                        "Scale9Height": 39,
                        "StretchWidthEnable": true,
                        "AnchorPoint": {
                          "ScaleX": 0.5,
                          "ScaleY": 0.5
                        },
                        "Position": {
                          "X": 127.5,
                          "Y": 0.0
                        },
                        "Scale": {
                          "ScaleX": 1.0,
                          "ScaleY": 1.0
                        },
                        "CColor": {},
                        "IconVisible": false,
                        "PrePosition": {
                          "X": 0.5,
                          "Y": 0.0
                        },
                        "PreSize": {
                          "X": 1.2941,
                          "Y": 0.0
                        },
                        "HorizontalEdge": "BothEdge",
                        "LeftMargin": -37.5,
                        "RightMargin": -37.5,
                        "TopMargin": -55.5,
                        "BottomMargin": -55.5,
                        "Tag": 148,
                        "ActionTag": 953529432,
                        "Size": {
                          "X": 330.0,
                          "Y": 111.0
                        },
                        "Name": "bgObjective",
                        "ctype": "ImageViewObjectData"
                      }
                    ],
                    "ActionTag": 1563789114,
                    "Size": {
                      "X": 255.0,
                      "Y": 0.0
                    },
                    "Name": "pObjective",
                    "ctype": "PanelObjectData"
                  }
                ],
                "ActionTag": 1264324759,
                "Size": {
                  "X": 662.0,
                  "Y": 174.0
                },
                "Name": "bgTop",
                "ctype": "ImageViewObjectData"
              },
              {
                "AnchorPoint": {},
                "Position": {
                  "X": 720.0,
                  "Y": -15.0
                },
                "Scale": {
                  "ScaleX": 1.0,
                  "ScaleY": 1.0
                },
                "CColor": {},
                "IconVisible": true,
                "PrePosition": {
                  "X": 1.0,
                  "Y": 0.0
                },
                "PreSize": {
                  "X": 0.0,
                  "Y": 0.0
                },
                "HorizontalEdge": "RightEdge",
                "VerticalEdge": "TopEdge",
                "LeftMargin": 720.0,
                "TopMargin": 15.0,
                "BottomMargin": -15.0,
                "Tag": 560,
                "Children": [
                  {
                    "FontSize": 14,
                    "ButtonText": "===",
                    "TextColor": {
                      "R": 0,
                      "G": 0,
                      "B": 0
                    },
                    "DisabledFileData": {
                      "Type": "Default",
                      "Path": "Default/Button_Disable.png",
                      "Plist": ""
                    },
                    "PressedFileData": {
                      "Type": "Default",
                      "Path": "Default/Button_Press.png",
                      "Plist": ""
                    },
                    "NormalFileData": {
                      "Type": "Default",
                      "Path": "Default/Button_Normal.png",
                      "Plist": ""
                    },
                    "Scale9Enable": true,
                    "Scale9OriginX": 15,
                    "Scale9OriginY": 11,
                    "Scale9Width": 16,
                    "Scale9Height": 14,
                    "OutlineColor": {
                      "G": 0,
                      "B": 0
                    },
                    "ShadowColor": {
                      "R": 110,
                      "G": 110,
                      "B": 110
                    },
                    "ShadowOffsetX": 2.0,
                    "ShadowOffsetY": -2.0,
                    "TouchEnable": true,
                    "AnchorPoint": {
                      "ScaleX": 0.5,
                      "ScaleY": 0.5
                    },
                    "Position": {
                      "X": -27.5,
                      "Y": -20.0
                    },
                    "Scale": {
                      "ScaleX": 1.0,
                      "ScaleY": 1.0
                    },
                    "CColor": {},
                    "IconVisible": false,
                    "PrePosition": {
                      "X": 0.0,
                      "Y": 0.0
                    },
                    "PreSize": {
                      "X": 0.0,
                      "Y": 0.0
                    },
                    "HorizontalEdge": "RightEdge",
                    "VerticalEdge": "TopEdge",
                    "LeftMargin": -50.0,
                    "RightMargin": 5.0,
                    "TopMargin": 5.0,
                    "BottomMargin": -35.0,
                    "Tag": 559,
                    "ActionTag": -105080433,
                    "Size": {
                      "X": 45.0,
                      "Y": 30.0
                    },
                    "Name": "btnTest",
                    "ctype": "ButtonObjectData"
                  },
                  {
                    "FontSize": 14,
                    "ButtonText": "Set Move",
                    "TextColor": {
                      "R": 0,
                      "G": 0,
                      "B": 0
                    },
                    "DisabledFileData": {
                      "Type": "Default",
                      "Path": "Default/Button_Disable.png",
                      "Plist": ""
                    },
                    "PressedFileData": {
                      "Type": "Default",
                      "Path": "Default/Button_Press.png",
                      "Plist": ""
                    },
                    "NormalFileData": {
                      "Type": "Default",
                      "Path": "Default/Button_Normal.png",
                      "Plist": ""
                    },
                    "Scale9Enable": true,
                    "Scale9OriginX": 15,
                    "Scale9OriginY": 11,
                    "Scale9Width": 16,
                    "Scale9Height": 14,
                    "OutlineColor": {
                      "G": 0,
                      "B": 0
                    },
                    "ShadowColor": {
                      "R": 110,
                      "G": 110,
                      "B": 110
                    },
                    "ShadowOffsetX": 2.0,
                    "ShadowOffsetY": -2.0,
                    "TouchEnable": true,
                    "AnchorPoint": {
                      "ScaleX": 0.5,
                      "ScaleY": 0.5
                    },
                    "Position": {
                      "X": -107.0043,
                      "Y": -68.2415
                    },
                    "Scale": {
                      "ScaleX": 1.0,
                      "ScaleY": 1.0
                    },
                    "CColor": {},
                    "IconVisible": false,
                    "PrePosition": {
                      "X": 0.0,
                      "Y": 0.0
                    },
                    "PreSize": {
                      "X": 0.0,
                      "Y": 0.0
                    },
                    "HorizontalEdge": "RightEdge",
                    "VerticalEdge": "BottomEdge",
                    "LeftMargin": -140.0043,
                    "RightMargin": 74.0043,
                    "TopMargin": 53.2415,
                    "BottomMargin": -83.2415,
                    "Tag": 561,
                    "ActionTag": 2017279633,
                    "Size": {
                      "X": 66.0,
                      "Y": 30.0
                    },
                    "Name": "btnTestSetMove",
                    "ctype": "ButtonObjectData"
                  },
                  {
                    "FontSize": 20,
                    "IsCustomSize": true,
                    "LabelText": "",
                    "PlaceHolderText": "1-100",
                    "MaxLengthText": 10,
                    "TouchEnable": true,
                    "AnchorPoint": {
                      "ScaleX": 0.5,
                      "ScaleY": 0.5
                    },
                    "Position": {
                      "X": -40.1262,
                      "Y": -68.7651
                    },
                    "Scale": {
                      "ScaleX": 1.0,
                      "ScaleY": 1.0
                    },
                    "CColor": {},
                    "IconVisible": false,
                    "PrePosition": {
                      "X": 0.0,
                      "Y": 0.0
                    },
                    "PreSize": {
                      "X": 0.0,
                      "Y": 0.0
                    },
                    "LeftMargin": -69.1262,
                    "RightMargin": 11.1262,
                    "TopMargin": 57.2651,
                    "BottomMargin": -80.2651,
                    "Tag": 562,
                    "ActionTag": 91356380,
                    "Size": {
                      "X": 58.0,
                      "Y": 23.0
                    },
                    "Name": "tfTestSetMove",
                    "ctype": "TextFieldObjectData"
                  }
                ],
                "ActionTag": -1807055315,
                "Size": {
                  "X": 0.0,
                  "Y": 0.0
                },
                "VisibleForFrame": false,
                "Name": "nodeTest",
                "ctype": "SingleNodeObjectData"
              },
              {
                "FileData": {
                  "Type": "Normal",
                  "Path": "game/element/3.png",
                  "Plist": ""
                },
                "BlendFunc": {
                  "Src": 1,
                  "Dst": 771
                },
                "AnchorPoint": {
                  "ScaleX": 0.5,
                  "ScaleY": 0.5
                },
                "Position": {
                  "X": 608.407,
                  "Y": -103.7946
                },
                "Scale": {
                  "ScaleX": 0.5,
                  "ScaleY": 0.5163
                },
                "CColor": {},
                "IconVisible": false,
                "PrePosition": {
                  "X": 0.845,
                  "Y": 0.0
                },
                "PreSize": {
                  "X": 0.0903,
                  "Y": 0.0
                },
                "HorizontalEdge": "RightEdge",
                "VerticalEdge": "TopEdge",
                "LeftMargin": 575.907,
                "RightMargin": 79.093,
                "TopMargin": 77.7946,
                "BottomMargin": -129.7946,
                "Tag": 563,
                "Children": [
                  {
                    "IsCustomSize": true,
                    "FontSize": 64,
                    "LabelText": "0",
                    "FontResource": {
                      "Type": "Normal",
                      "Path": "font/BalooPaaji2-Bold.ttf",
                      "Plist": ""
                    },
                    "OutlineSize": 2,
                    "OutlineColor": {
                      "R": 205,
                      "G": 68,
                      "B": 35
                    },
                    "OutlineEnabled": true,
                    "ShadowColor": {
                      "R": 205,
                      "G": 68,
                      "B": 35
                    },
                    "ShadowOffsetX": 2.0,
                    "ShadowOffsetY": -2.0,
                    "AnchorPoint": {
                      "ScaleY": 0.5
                    },
                    "Position": {
                      "X": 76.0812,
                      "Y": 20.9175
                    },
                    "Scale": {
                      "ScaleX": 1.0,
                      "ScaleY": 1.0
                    },
                    "CColor": {},
                    "IconVisible": false,
                    "PrePosition": {
                      "X": 1.1705,
                      "Y": 0.4023
                    },
                    "PreSize": {
                      "X": 1.5385,
                      "Y": 1.6154
                    },
                    "LeftMargin": 76.0812,
                    "RightMargin": -111.0812,
                    "TopMargin": -10.9175,
                    "BottomMargin": -21.0825,
                    "Tag": 564,
                    "ActionTag": 1231926937,
                    "Size": {
                      "X": 100.0,
                      "Y": 84.0
                    },
                    "Name": "amountCollect",
                    "ctype": "TextObjectData"
                  }
                ],
                "ActionTag": -755815572,
                "Size": {
                  "X": 65.0,
                  "Y": 52.0
                },
                "VisibleForFrame": false,
                "Name": "iconCollect",
                "ctype": "SpriteObjectData"
              },
              {
                "FontSize": 25,
                "LabelText": "I need to clear \nthese Wooden Crates\nto make apath!",
                "FontResource": {
                  "Type": "Normal",
                  "Path": "font/BalooPaaji2-Bold.ttf",
                  "Plist": ""
                },
                "HorizontalAlignmentType": "HT_Center",
                "VerticalAlignmentType": "VT_Center",
                "OutlineColor": {
                  "G": 0,
                  "B": 0
                },
                "ShadowColor": {
                  "R": 110,
                  "G": 110,
                  "B": 110
                },
                "ShadowOffsetX": 2.0,
                "ShadowOffsetY": -2.0,
                "AnchorPoint": {
                  "ScaleY": 1.0
                },
                "Position": {
                  "X": 160.0,
                  "Y": -245.0
                },
                "Scale": {
                  "ScaleX": 1.0,
                  "ScaleY": 1.0
                },
                "CColor": {},
                "IconVisible": false,
                "PrePosition": {
                  "X": 0.2222,
                  "Y": 0.0
                },
                "PreSize": {
                  "X": 0.3375,
                  "Y": 0.0
                },
                "LeftMargin": 160.0,
                "RightMargin": 317.0,
                "TopMargin": 245.0,
                "BottomMargin": -338.0,
                "Tag": 37,
                "Children": [
                  {
                    "FileData": {
                      "Type": "Normal",
                      "Path": "game/gui/end_game/talk_bubble.png",
                      "Plist": ""
                    },
                    "Scale9Enable": true,
                    "Scale9OriginX": 135,
                    "Scale9OriginY": 105,
                    "Scale9Width": 389,
                    "Scale9Height": 218,
                    "StretchWidthEnable": true,
                    "StretchHeightEnable": true,
                    "AnchorPoint": {
                      "ScaleX": 0.5,
                      "ScaleY": 0.5
                    },
                    "Position": {
                      "X": 121.5,
                      "Y": 65.0
                    },
                    "Scale": {
                      "ScaleX": 1.0,
                      "ScaleY": 1.0
                    },
                    "CColor": {},
                    "IconVisible": false,
                    "PrePosition": {
                      "X": 0.5,
                      "Y": 0.6989
                    },
                    "PreSize": {
                      "X": 1.3086,
                      "Y": 1.9462
                    },
                    "HorizontalEdge": "BothEdge",
                    "VerticalEdge": "BothEdge",
                    "LeftMargin": -37.5,
                    "RightMargin": -37.5,
                    "TopMargin": -62.5,
                    "BottomMargin": -25.5,
                    "Tag": 38,
                    "ActionTag": -981704754,
                    "Size": {
                      "X": 318.0,
                      "Y": 181.0
                    },
                    "Name": "imgBubble",
                    "ctype": "ImageViewObjectData"
                  },
                  {
                    "FontSize": 25,
                    "LabelText": "I need to clear \nthese Wooden Crates\nto make a path!",
                    "FontResource": {
                      "Type": "Normal",
                      "Path": "font/BalooPaaji2-Bold.ttf",
                      "Plist": ""
                    },
                    "HorizontalAlignmentType": "HT_Center",
                    "VerticalAlignmentType": "VT_Center",
                    "OutlineColor": {
                      "G": 0,
                      "B": 0
                    },
                    "ShadowColor": {
                      "R": 110,
                      "G": 110,
                      "B": 110
                    },
                    "ShadowOffsetX": 2.0,
                    "ShadowOffsetY": -2.0,
                    "AnchorPoint": {
                      "ScaleX": 0.5,
                      "ScaleY": 0.5
                    },
                    "Position": {
                      "X": 121.5,
                      "Y": 46.5
                    },
                    "Scale": {
                      "ScaleX": 1.0,
                      "ScaleY": 1.0
                    },
                    "CColor": {
                      "R": 180,
                      "G": 113,
                      "B": 75
                    },
                    "IconVisible": false,
                    "PositionPercentXEnabled": true,
                    "PositionPercentYEnabled": true,
                    "PrePosition": {
                      "X": 0.5,
                      "Y": 0.5
                    },
                    "PreSize": {
                      "X": 1.0,
                      "Y": 1.0
                    },
                    "Tag": 39,
                    "ActionTag": -324871114,
                    "Size": {
                      "X": 243.0,
                      "Y": 93.0
                    },
                    "Name": "lbTextBubblePhantom",
                    "ctype": "TextObjectData"
                  }
                ],
                "ActionTag": 658850016,
                "Size": {
                  "X": 243.0,
                  "Y": 93.0
                },
                "Name": "lbTextBubble",
                "ctype": "TextObjectData"
              }
            ],
            "ActionTag": -1323258253,
            "Size": {
              "X": 720.0,
              "Y": 0.0
            },
            "Name": "pInfo",
            "ctype": "PanelObjectData"
          },
          {
            "ClipAble": false,
            "BackColorAlpha": 102,
            "SingleColor": {
              "R": 0,
              "G": 0,
              "B": 0
            },
            "FirstColor": {
              "R": 150,
              "G": 200
            },
            "EndColor": {},
            "ColorVector": {
              "ScaleY": 1.0
            },
            "Scale9Width": 1,
            "Scale9Height": 1,
            "AnchorPoint": {
              "ScaleX": 0.5,
              "ScaleY": 0.5
            },
            "Position": {
              "X": 360.0,
              "Y": 640.0
            },
            "Scale": {
              "ScaleX": 1.0,
              "ScaleY": 1.0
            },
            "CColor": {},
            "IconVisible": false,
            "PositionPercentXEnabled": true,
            "PositionPercentYEnabled": true,
            "PrePosition": {
              "X": 0.5,
              "Y": 0.5
            },
            "PercentWidthEnable": true,
            "PercentHeightEnable": true,
            "PercentWidthEnabled": true,
            "PercentHeightEnabled": true,
            "PreSize": {
              "X": 1.0,
              "Y": 1.0
            },
            "Tag": 288,
            "Children": [
              {
                "ClipAble": false,
                "BackColorAlpha": 216,
                "ComboBoxIndex": 1,
                "SingleColor": {
                  "R": 0,
                  "G": 0,
                  "B": 0
                },
                "FirstColor": {
                  "R": 150,
                  "G": 200
                },
                "EndColor": {},
                "ColorVector": {
                  "ScaleY": 1.0
                },
                "Scale9Width": 1,
                "Scale9Height": 1,
                "TouchEnable": true,
                "AnchorPoint": {
                  "ScaleX": 0.5,
                  "ScaleY": 0.5
                },
                "Position": {
                  "X": 360.0,
                  "Y": 640.0
                },
                "Scale": {
                  "ScaleX": 1.0,
                  "ScaleY": 1.0
                },
                "CColor": {},
                "IconVisible": false,
                "PositionPercentXEnabled": true,
                "PositionPercentYEnabled": true,
                "PrePosition": {
                  "X": 0.5,
                  "Y": 0.5
                },
                "PercentWidthEnable": true,
                "PercentHeightEnable": true,
                "PercentWidthEnabled": true,
                "PercentHeightEnabled": true,
                "PreSize": {
                  "X": 1.0,
                  "Y": 1.0
                },
                "Tag": 289,
                "ActionTag": -270212900,
                "Size": {
                  "X": 720.0,
                  "Y": 1280.0
                },
                "Name": "pFogIntroObjective",
                "ctype": "PanelObjectData"
              },
              {
                "AnchorPoint": {},
                "Position": {
                  "X": 360.0,
                  "Y": 640.0
                },
                "Scale": {
                  "ScaleX": 1.0,
                  "ScaleY": 1.0
                },
                "RotationSkewX": -13.4451,
                "RotationSkewY": -13.4434,
                "CColor": {},
                "IconVisible": true,
                "PositionPercentXEnabled": true,
                "PositionPercentYEnabled": true,
                "PrePosition": {
                  "X": 0.5,
                  "Y": 0.5
                },
                "PreSize": {
                  "X": 0.0,
                  "Y": 0.0
                },
                "LeftMargin": 360.0,
                "RightMargin": 360.0,
                "TopMargin": 640.0,
                "BottomMargin": 640.0,
                "Tag": 59,
                "Children": [
                  {
                    "ClipAble": false,
                    "BackColorAlpha": 102,
                    "SingleColor": {
                      "R": 150,
                      "G": 200
                    },
                    "FirstColor": {
                      "R": 150,
                      "G": 200
                    },
                    "EndColor": {},
                    "ColorVector": {
                      "ScaleY": 1.0
                    },
                    "Scale9OriginX": -598,
                    "Scale9OriginY": -83,
                    "Scale9Width": 1196,
                    "Scale9Height": 166,
                    "AnchorPoint": {
                      "ScaleX": 0.5,
                      "ScaleY": 0.5
                    },
                    "Position": {
                      "X": 0.0,
                      "Y": 0.0
                    },
                    "Scale": {
                      "ScaleX": 1.0,
                      "ScaleY": 1.0
                    },
                    "CColor": {},
                    "IconVisible": false,
                    "PrePosition": {
                      "X": 0.0,
                      "Y": 0.0
                    },
                    "PreSize": {
                      "X": 0.0,
                      "Y": 0.0
                    },
                    "LeftMargin": -1440.0,
                    "RightMargin": -1440.0,
                    "TopMargin": -100.0,
                    "BottomMargin": -100.0,
                    "Tag": 60,
                    "Children": [
                      {
                        "FileData": {
                          "Type": "Normal",
                          "Path": "game/gui/start_game/monster_banner_0.png",
                          "Plist": ""
                        },
                        "Scale9OriginX": 598,
                        "Scale9OriginY": 83,
                        "Scale9Width": 617,
                        "Scale9Height": 86,
                        "AnchorPoint": {
                          "ScaleX": 0.5,
                          "ScaleY": 0.5
                        },
                        "Position": {
                          "X": 1440.0,
                          "Y": 100.0
                        },
                        "Scale": {
                          "ScaleX": 1.0,
                          "ScaleY": 1.0
                        },
                        "CColor": {},
                        "IconVisible": false,
                        "PositionPercentXEnabled": true,
                        "PositionPercentYEnabled": true,
                        "PrePosition": {
                          "X": 0.5,
                          "Y": 0.5
                        },
                        "PreSize": {
                          "X": 0.6295,
                          "Y": 1.26
                        },
                        "LeftMargin": 533.5,
                        "RightMargin": 533.5,
                        "TopMargin": -26.0,
                        "BottomMargin": -26.0,
                        "Tag": 291,
                        "ActionTag": -301997056,
                        "Size": {
                          "X": 1813.0,
                          "Y": 252.0
                        },
                        "Name": "imgMonsterBg",
                        "ctype": "ImageViewObjectData"
                      }
                    ],
                    "ActionTag": 32991113,
                    "Size": {
                      "X": 2880.0,
                      "Y": 200.0
                    },
                    "Name": "pBgMonster",
                    "ctype": "PanelObjectData"
                  },
                  {
                    "AnchorPoint": {},
                    "Position": {
                      "X": -180.0,
                      "Y": 0.0
                    },
                    "Scale": {
                      "ScaleX": 1.0,
                      "ScaleY": 1.0
                    },
                    "CColor": {},
                    "IconVisible": true,
                    "PrePosition": {
                      "X": 0.0,
                      "Y": 0.0
                    },
                    "PreSize": {
                      "X": 0.0,
                      "Y": 0.0
                    },
                    "LeftMargin": -180.0,
                    "RightMargin": 180.0,
                    "Tag": 293,
                    "ActionTag": 1625151730,
                    "Size": {
                      "X": 0.0,
                      "Y": 0.0
                    },
                    "Name": "nodeMonsterSprite",
                    "ctype": "SingleNodeObjectData"
                  },
                  {
                    "IsCustomSize": true,
                    "FontSize": 75,
                    "LabelText": "Khi\nHieu Chien",
                    "FontResource": {
                      "Type": "Normal",
                      "Path": "font/BalooPaaji2-ExtraBold.ttf",
                      "Plist": ""
                    },
                    "HorizontalAlignmentType": "HT_Center",
                    "VerticalAlignmentType": "VT_Center",
                    "OutlineSize": 7,
                    "OutlineColor": {
                      "R": 26,
                      "G": 26,
                      "B": 26
                    },
                    "OutlineEnabled": true,
                    "ShadowColor": {
                      "R": 110,
                      "G": 110,
                      "B": 110
                    },
                    "ShadowOffsetX": 2.0,
                    "ShadowOffsetY": -2.0,
                    "AnchorPoint": {
                      "ScaleX": 0.5,
                      "ScaleY": 0.5
                    },
                    "Position": {
                      "X": 180.0,
                      "Y": 10.0
                    },
                    "Scale": {
                      "ScaleX": 1.0,
                      "ScaleY": 1.0
                    },
                    "RotationSkewX": 13.1325,
                    "RotationSkewY": 13.1338,
                    "CColor": {},
                    "IconVisible": false,
                    "PrePosition": {
                      "X": 0.0,
                      "Y": 0.0
                    },
                    "PreSize": {
                      "X": 0.0,
                      "Y": 0.0
                    },
                    "LeftMargin": -50.0,
                    "RightMargin": -410.0,
                    "TopMargin": -135.0,
                    "BottomMargin": -115.0,
                    "Tag": 292,
                    "ActionTag": 2046896651,
                    "Size": {
                      "X": 460.0,
                      "Y": 250.0
                    },
                    "Name": "lbMonsterName",
                    "ctype": "TextObjectData"
                  }
                ],
                "ActionTag": -94953190,
                "Size": {
                  "X": 0.0,
                  "Y": 0.0
                },
                "Name": "nodeMonster",
                "ctype": "SingleNodeObjectData"
              },
              {
                "AnchorPoint": {},
                "Position": {
                  "X": 360.0,
                  "Y": 640.0
                },
                "Scale": {
                  "ScaleX": 1.0,
                  "ScaleY": 1.0
                },
                "CColor": {},
                "IconVisible": true,
                "PositionPercentXEnabled": true,
                "PositionPercentYEnabled": true,
                "PrePosition": {
                  "X": 0.5,
                  "Y": 0.5
                },
                "PreSize": {
                  "X": 0.0,
                  "Y": 0.0
                },
                "LeftMargin": 360.0,
                "RightMargin": 360.0,
                "TopMargin": 640.0,
                "BottomMargin": 640.0,
                "Tag": 284,
                "Children": [
                  {
                    "FileData": {
                      "Type": "Normal",
                      "Path": "game/gui/start_game/smiling_cat.png",
                      "Plist": ""
                    },
                    "Scale9OriginX": 106,
                    "Scale9OriginY": 87,
                    "Scale9Width": 112,
                    "Scale9Height": 92,
                    "AnchorPoint": {},
                    "Position": {
                      "X": -382.0,
                      "Y": 85.0
                    },
                    "Scale": {
                      "ScaleX": 1.0,
                      "ScaleY": 1.0
                    },
                    "CColor": {},
                    "IconVisible": false,
                    "PrePosition": {
                      "X": 0.0,
                      "Y": 0.0
                    },
                    "PreSize": {
                      "X": 0.0,
                      "Y": 0.0
                    },
                    "HorizontalEdge": "LeftEdge",
                    "VerticalEdge": "TopEdge",
                    "LeftMargin": -382.0,
                    "RightMargin": 58.0,
                    "TopMargin": -351.0,
                    "BottomMargin": 85.0,
                    "Tag": 287,
                    "ActionTag": -1775750152,
                    "Size": {
                      "X": 324.0,
                      "Y": 266.0
                    },
                    "Name": "imgCatObj",
                    "ctype": "ImageViewObjectData"
                  },
                  {
                    "FileData": {
                      "Type": "Normal",
                      "Path": "game/gui/start_game/start_game_objective_bg.png",
                      "Plist": ""
                    },
                    "Scale9OriginX": 272,
                    "Scale9OriginY": 62,
                    "Scale9Width": 281,
                    "Scale9Height": 66,
                    "AnchorPoint": {
                      "ScaleX": 0.5,
                      "ScaleY": 0.5
                    },
                    "Position": {
                      "X": 0.0,
                      "Y": 0.0
                    },
                    "Scale": {
                      "ScaleX": 1.0,
                      "ScaleY": 1.0
                    },
                    "CColor": {},
                    "IconVisible": false,
                    "PrePosition": {
                      "X": 0.0,
                      "Y": 0.0
                    },
                    "PreSize": {
                      "X": 0.0,
                      "Y": 0.0
                    },
                    "LeftMargin": -412.5,
                    "RightMargin": -412.5,
                    "TopMargin": -95.0,
                    "BottomMargin": -95.0,
                    "Tag": 286,
                    "ActionTag": -343939790,
                    "Size": {
                      "X": 825.0,
                      "Y": 190.0
                    },
                    "Name": "bgObjIntro",
                    "ctype": "ImageViewObjectData"
                  },
                  {
                    "ClipAble": false,
                    "BackColorAlpha": 102,
                    "SingleColor": {
                      "R": 150,
                      "G": 200
                    },
                    "FirstColor": {
                      "R": 150,
                      "G": 200
                    },
                    "EndColor": {},
                    "ColorVector": {
                      "ScaleY": 1.0
                    },
                    "Scale9Width": 1,
                    "Scale9Height": 1,
                    "AnchorPoint": {
                      "ScaleX": 0.5,
                      "ScaleY": 0.5
                    },
                    "Position": {
                      "X": 0.0,
                      "Y": 0.0
                    },
                    "Scale": {
                      "ScaleX": 1.0,
                      "ScaleY": 1.0
                    },
                    "CColor": {},
                    "IconVisible": false,
                    "PrePosition": {
                      "X": 0.0,
                      "Y": 0.0
                    },
                    "PreSize": {
                      "X": 0.0,
                      "Y": 0.0
                    },
                    "LeftMargin": -100.0,
                    "RightMargin": -100.0,
                    "Tag": 290,
                    "ActionTag": 469528977,
                    "Size": {
                      "X": 200.0,
                      "Y": 0.0
                    },
                    "Name": "pObjectiveIntro",
                    "ctype": "PanelObjectData"
                  }
                ],
                "ActionTag": -1282448473,
                "Size": {
                  "X": 0.0,
                  "Y": 0.0
                },
                "Name": "nodeObjectives",
                "ctype": "SingleNodeObjectData"
              }
            ],
            "ActionTag": 1615952287,
            "Size": {
              "X": 720.0,
              "Y": 1280.0
            },
            "Name": "pIntro",
            "ctype": "PanelObjectData"
          },
          {
            "FileData": {
              "Type": "Normal",
              "Path": "common/alert_180min.png",
              "Plist": ""
            },
            "BlendFunc": {
              "Src": 1,
              "Dst": 771
            },
            "AnchorPoint": {
              "ScaleY": 1.0
            },
            "Position": {
              "X": 15.0,
              "Y": 1030.0
            },
            "Scale": {
              "ScaleX": 1.0,
              "ScaleY": 1.0
            },
            "CColor": {},
            "IconVisible": false,
            "PrePosition": {
              "X": 0.0208,
              "Y": 0.8047
            },
            "PreSize": {
              "X": 0.4306,
              "Y": 0.0766
            },
            "HorizontalEdge": "LeftEdge",
            "VerticalEdge": "TopEdge",
            "LeftMargin": 15.0,
            "RightMargin": 395.0,
            "TopMargin": 250.0,
            "BottomMargin": 932.0,
            "Tag": 511,
            "ActionTag": -2122961041,
            "Size": {
              "X": 310.0,
              "Y": 98.0
            },
            "VisibleForFrame": false,
            "Alpha": 127,
            "Name": "alert_180min_18",
            "ctype": "SpriteObjectData"
          }
        ],
        "Size": {
          "X": 720.0,
          "Y": 1280.0
        },
        "Name": "Layer",
        "ctype": "LayerObjectData"
      },
      "UsedResources": [
        "../../common/alert_180min.png",
        "../../Default/Button_Disable.png",
        "../../Default/Button_Normal.png",
        "../../Default/Button_Press.png",
        "../../font/BalooPaaji2-Bold.ttf",
        "../../font/BalooPaaji2-ExtraBold.ttf",
        "../../game/element/3.png",
        "../../game/gui/board_info/bg_cat.png",
        "../../game/gui/board_info/bg_cat_border.png",
        "../../game/gui/board_info/bg_move.png",
        "../../game/gui/board_info/bg_objective.png",
        "../../game/gui/board_info/bg_top.png",
        "../../game/gui/end_game/talk_bubble.png",
        "../../game/gui/start_game/monster_banner_0.png",
        "../../game/gui/start_game/smiling_cat.png",
        "../../game/gui/start_game/start_game_objective_bg.png"
      ],
      "ctype": "GameFileData"
    }
  },
  "Type": "Layer"
}