{"shareId":-1,"shareTime":0,"levelId":148,"mapName":"Level 148 fix","difficulty":1,"move":19,"listPercent":{"1":15,"2":15,"3":15,"6":15},"m":-0.8,"r":-0.2,"s":2,"dM":0.1,"dR":0.1,"dA":1,"listTarget":{"1000":1,"2900":6},"listElementByGrid":{"0":[[10,1,0,0,0,null],[2900,7]],"1":[[10,1,0,0,0,null]],"2":[[10,1,0,0,0,null],[900,1]],"3":[[10,1,0,0,0,null],[900,1]],"4":[[10,1,0,0,0,null],[1100,"2"]],"5":[[10,1,0,0,0,null],[3]],"6":[[10,1,0,0,0,null],[3]],"7":[[10,1,0,0,0,null],[2]],"8":[[10,1,0,0,0,null],[1000,null,null]],"9":[[10,0,0,0,0,null]],"10":[[10,0,0,0,0,null]],"11":[[10,0,0,0,0,null],[900,1]],"12":[[10,0,0,0,0,null],[900,1]],"13":[[10,0,0,0,0,null],[1100,"2"]],"14":[[10,0,0,0,0,null],[2]],"15":[[10,0,0,0,0,null],[3]],"16":[[10,0,0,0,0,null],[6]],"17":[[10,0,0,0,0,null],[2]],"18":[[10,0,0,0,0,null],[2900,7]],"19":[[10,0,0,0,0,null]],"20":[[10,0,0,0,0,null],[900,1]],"21":[[10,0,0,0,0,null],[900,1]],"22":[[10,0,0,0,0,null],[1100,"2"]],"23":[[10,0,0,0,0,null],[3]],"24":[[10,0,0,0,0,null],[1]],"25":[[10,0,0,0,0,null],[2]],"26":[[10,0,0,0,0,null],[1]],"27":[[10,0,0,0,0,null]],"28":[[10,0,0,0,0,null]],"29":[[10,0,0,0,0,null],[900,1]],"30":[[10,0,0,0,0,null],[900,1]],"31":[[10,0,0,0,0,null],[1100,"2"]],"32":[[10,0,0,0,0,null],[1]],"33":[[10,0,0,0,0,null],[3]],"34":[[10,0,0,0,0,null],[1]],"35":[[10,0,0,0,0,null],[1]],"36":[[10,0,0,0,0,null],[2900,7]],"37":[[10,0,0,0,0,null]],"38":[[10,0,0,0,0,null],[900,1]],"39":[[10,0,0,0,0,null],[900,1]],"40":[[10,0,0,0,0,null],[1100,"2"]],"41":[[10,0,0,0,0,null],[1100,"2"]],"42":[[10,0,0,0,0,null],[1100,"2"]],"43":[[10,0,0,0,0,null],[1100,"2"]],"44":[[10,0,0,0,0,null],[1100,"2"]],"45":[[10,0,1,0,0,null]],"46":[[10,0,1,0,0,null]],"47":[[10,0,0,0,0,null],[900,1]],"48":[[10,0,0,0,0,null],[900,1]],"49":[[10,0,0,0,0,null],[900,1]],"50":[[10,0,0,0,0,null],[900,1]],"51":[[10,0,0,0,0,null],[900,1]],"52":[[10,0,0,0,0,null],[900,1]],"53":[[10,0,0,0,0,null],[900,1]],"56":[[10,0,1,0,0,null],[900,1]],"57":[[10,0,0,0,0,null],[900,1]],"58":[[10,0,0,0,0,null],[900,1]],"59":[[10,0,0,0,0,null],[900,1]],"60":[[10,0,0,0,0,null],[900,1]],"61":[[10,0,0,0,0,null],[900,1]],"62":[[10,0,0,0,0,null],[900,1]],"66":[[10,0,0,0,0,null],[2900,7]],"67":[[10,0,0,0,0,null]],"68":[[10,0,0,0,0,null],[2900,7]],"69":[[10,0,0,0,0,null]],"70":[[10,0,0,0,0,null],[2900,7]],"71":[[10,0,0,0,0,null]],"75":[[10,0,1,0,0,null]],"76":[[10,0,1,0,0,null]],"77":[[10,0,1,0,0,null]],"78":[[10,0,1,0,0,null]],"79":[[10,0,1,0,0,null]],"80":[[10,0,1,0,0,null]],"-22":[[1600]]}}